promptmodel/STARTER.py
promptmodel/__init__.py
promptmodel/chat_model.py
promptmodel/constants.py
promptmodel/dev_app.py
promptmodel/function_model.py
promptmodel/promptmodel_init.py
promptmodel/unit_logger.py
promptmodel/apis/__init__.py
promptmodel/apis/base.py
promptmodel/cli/__init__.py
promptmodel/cli/main.py
promptmodel/cli/signal_handler.py
promptmodel/cli/utils.py
promptmodel/cli/commands/__init__.py
promptmodel/cli/commands/configure.py
promptmodel/cli/commands/connect.py
promptmodel/cli/commands/dev.py
promptmodel/cli/commands/fix.py
promptmodel/cli/commands/init.py
promptmodel/cli/commands/login.py
promptmodel/cli/commands/project.py
promptmodel/database/__init__.py
promptmodel/database/config.py
promptmodel/database/crud.py
promptmodel/database/crud_chat.py
promptmodel/database/models.py
promptmodel/database/models_chat.py
promptmodel/database/orm.py
promptmodel/llms/__init__.py
promptmodel/llms/llm.py
promptmodel/llms/llm_dev.py
promptmodel/llms/llm_proxy.py
promptmodel/types/__init__.py
promptmodel/types/enums.py
promptmodel/types/request.py
promptmodel/types/response.py
promptmodel/utils/__init__.py
promptmodel/utils/async_utils.py
promptmodel/utils/config_utils.py
promptmodel/utils/crypto.py
promptmodel/utils/logger.py
promptmodel/utils/output_utils.py
promptmodel/utils/random_utils.py
promptmodel/utils/token_counting.py
promptmodel/websocket/__init__.py
promptmodel/websocket/reload_handler.py
promptmodel/websocket/websocket_client.py
tests/__init__.py
tests/constants.py
tests/api_client/__init__.py
tests/api_client/api_client_test.py
tests/chat_model/__init__.py
tests/chat_model/chat_model_test.py
tests/chat_model/conftest.py
tests/chat_model/registering_meta_test.py
tests/cli/dev_test.py
tests/function_model/__init__.py
tests/function_model/conftest.py
tests/function_model/function_model_test.py
tests/function_model/registering_meta_test.py
tests/llm/__init__.py
tests/llm/error_case_test.py
tests/llm/function_call_test.py
tests/llm/parse_test.py
promptmodel-0.2.1.dist-info/LICENSE
promptmodel-0.2.1.dist-info/METADATA
promptmodel-0.2.1.dist-info/WHEEL
promptmodel-0.2.1.dist-info/entry_points.txt
promptmodel-0.2.1.dist-info/top_level.txt
promptmodel-0.2.1.dist-info/RECORD
