Metadata-Version: 2.1
Name: promptmodel
Version: 0.2.1
Summary: Prompt & model versioning on the cloud, built for developers.
Home-page: https://github.com/weavel-ai/promptmodel
Author: weavel
Keywords: weavel,agent,llm,tools,promptmodel,llm agent,prompt,versioning,eval,evaluation,collaborative
Requires-Python: >=3.8.10
License-File: LICENSE
Requires-Dist: httpx[http2]
Requires-Dist: pydantic >=2.4.2
Requires-Dist: peewee
Requires-Dist: typer[all]
Requires-Dist: cryptography
Requires-Dist: pyyaml
Requires-Dist: InquirerPy
Requires-Dist: litellm >=1.7.1
Requires-Dist: python-dotenv
Requires-Dist: websockets
Requires-Dist: termcolor
Requires-Dist: watchdog
Requires-Dist: readerwriterlock
Requires-Dist: nest-asyncio
